QAStrategy/__init__.py
QAStrategy/qactabase.py
QAStrategy/qahedgebase.py
QAStrategy/qastockbase.py
QAStrategy/qastrategybase.py
QAStrategy/setting.py
QAStrategy/strategywithreal.py
QAStrategy/util.py
QAStrategy-0.0.25.dist-info/LICENSE
QAStrategy-0.0.25.dist-info/METADATA
QAStrategy-0.0.25.dist-info/WHEEL
QAStrategy-0.0.25.dist-info/top_level.txt
QAStrategy-0.0.25.dist-info/zip-safe
QAStrategy-0.0.25.dist-info/RECORD
