Metadata-Version: 2.1
Name: QAStrategy
Version: 0.0.25
Summary: QUANTAXIS:Quantitative Financial Strategy Framework
Home-page: https://github.com/yutiansut/QAStrategy
Author: yutiansut
Author-email: yutiansut@qq.com
License: MIT
Keywords: quantaxis,quant,finance,Backtest,Framework
Platform: UNKNOWN
Classifier: License :: OSI Approved :: MIT License
Classifier: Programming Language :: Python
Classifier: Intended Audience :: Developers
Classifier: Operating System :: OS Independent
Requires-Dist: quantaxis
Requires-Dist: qaenv
Requires-Dist: qifiaccount
Requires-Dist: quantaxis-pubsub
